{
  "formatVersion": 1,
  "database": {
    "version": 7,
    "identityHash": "5beca3416c8015ad7e42d665919986e5",
    "entities": [
      {
        "tableName": "pathTable",
        "createSql": "CREATE TABLE IF NOT EXISTS `${TABLE_NAME}` (`id` INTEGER PRIMARY KEY AUTOINCREMENT, `drawingTool` TEXT NOT NULL, `path` TEXT NOT NULL, `strokeWidth` REAL NOT NULL, `strokeColor` INTEGER NOT NULL, `backgroundColor` INTEGER NOT NULL, `opacity` REAL NOT NULL, `whiteBoardId` INTEGER NOT NULL)",
        "fields": [
          {
            "fieldPath": "id",
            "columnName": "id",
            "affinity": "INTEGER"
          },
          {
            "fieldPath": "drawingTool",
            "columnName": "drawingTool",
            "affinity": "TEXT",
            "notNull": true
          },
          {
            "fieldPath": "path",
            "columnName": "path",
            "affinity": "TEXT",
            "notNull": true
          },
          {
            "fieldPath": "strokeWidth",
            "columnName": "strokeWidth",
            "affinity": "REAL",
            "notNull": true
          },
          {
            "fieldPath": "strokeColor",
            "columnName": "strokeColor",
            "affinity": "INTEGER",
            "notNull": true
          },
          {
            "fieldPath": "backgroundColor",
            "columnName": "backgroundColor",
            "affinity": "INTEGER",
            "notNull": true
          },
          {
            "fieldPath": "opacity",
            "columnName": "opacity",
            "affinity": "REAL",
            "notNull": true
          },
          {
            "fieldPath": "whiteBoardId",
            "columnName": "whiteBoardId",
            "affinity": "INTEGER",
            "notNull": true
          }
        ],
        "primaryKey": {
          "autoGenerate": true,
          "columnNames": [
            "id"
          ]
        }
      },
      {
        "tableName": "whiteboard_table",
        "createSql": "CREATE TABLE IF NOT EXISTS `${TABLE_NAME}` (`id` INTEGER PRIMARY KEY AUTOINCREMENT, `name` TEXT NOT NULL, `lastEdited` TEXT NOT NULL, `canvasColor` INTEGER NOT NULL)",
        "fields": [
          {
            "fieldPath": "id",
            "columnName": "id",
            "affinity": "INTEGER"
          },
          {
            "fieldPath": "name",
            "columnName": "name",
            "affinity": "TEXT",
            "notNull": true
          },
          {
            "fieldPath": "lastEdited",
            "columnName": "lastEdited",
            "affinity": "TEXT",
            "notNull": true
          },
          {
            "fieldPath": "canvasColor",
            "columnName": "canvasColor",
            "affinity": "INTEGER",
            "notNull": true
          }
        ],
        "primaryKey": {
          "autoGenerate": true,
          "columnNames": [
            "id"
          ]
        }
      }
    ],
    "setupQueries": [
      "CREATE TABLE IF NOT EXISTS room_master_table (id INTEGER PRIMARY KEY,identity_hash TEXT)",
      "INSERT OR REPLACE INTO room_master_table (id,identity_hash) VALUES(42, '5beca3416c8015ad7e42d665919986e5')"
    ]
  }
}